sota_asr/__init__.py
sota_asr/__main__.py
sota_asr/inference/__init__.py
sota_asr/inference/base.py
sota_asr/inference/ort.py
sota_asr/inference/pth.py
sota_asr/utils.py
sota_asr-0.1.0.dist-info/METADATA
sota_asr-0.1.0.dist-info/WHEEL
sota_asr-0.1.0.dist-info/entry_points.txt
sota_asr-0.1.0.dist-info/RECORD
