Metadata-Version: 2.1
Name: sota-asr
Version: 0.1.0
Summary: 基于funasr的语音识别服务
Author: wangmengdi06
Author-email: wangmengdi06@58.com
Requires-Python: >=3.10,<4.0
Classifier: Programming Language :: Python :: 3
Classifier: Programming Language :: Python :: 3.10
Classifier: Programming Language :: Python :: 3.11
Classifier: Programming Language :: Python :: 3.12
Provides-Extra: onnx
Requires-Dist: funasr (>=1.0.27)
Requires-Dist: funasr-onnx (>=0.3.1) ; extra == "onnx"
Requires-Dist: jsonargparse (>=4.29.0,<5.0.0)
Requires-Dist: librosa (>=0.10.2)
Requires-Dist: lightning_utilities (>=0.11.2)
Requires-Dist: loguru (>=0.7.2)
Requires-Dist: modelscope (>=1.14.0)
Requires-Dist: onnxruntime (>=0.18.0) ; extra == "onnx"
